Metadata-Version: 2.1
Name: RoticSDK-Python
Version: 2.0.6.1
Summary: Python SDK let you call Rotic Intelligent Solutions API
Home-page: https://github.com/roticmedia/RoticSDK-Python
Author: Rotic Intelligent Solutions
Author-email: dev@rotic.ir
License: UNKNOWN
Platform: UNKNOWN
Classifier: Programming Language :: Python :: 3
Classifier: License :: OSI Approved :: MIT License
Classifier: Operating System :: OS Independent
License-File: LICENSE
